{
    "routeType":  "AssignRouteType_Block_Pass",
    "name":  "football/Playbooks/PlayLibrary/Assignments/Halfback/SG_H2_Delay_Backstep_FakeHand_PassBlock_HBBehind",
    "steps":  [
                  {
                      "guid":  "1a2f27ee-49a6-49c2-a791-6ae17d27bb41",
                      "data":  {
                                   "opCodeEX":  "ID_CANNEDHANDOFF",
                                   "handoffAnim":  "23",
                                   "playerNum":  "HandoffPlayerSlot_O1",
                                   "flippedHandoffAnim":  "21"
                               },
                      "type":  "CannedHandoffAssignment"
                  },
                  {
                      "guid":  "a05916b2-646e-4ddb-bc76-bcc161c5f7cb",
                      "data":  {
                                   "optionalInitalDirection":  "-1",
                                   "opCodeEX":  "ID_INITIALMOVE",
                                   "anim":  "MOVETYPE_BACKSTEP",
                                   "direction":  "155"
                               },
                      "type":  "InitialAnimAssignment"
                  },
                  {
                      "guid":  "129147ad-3b4a-4a43-b23c-7cc17d4210a0",
                      "data":  {
                                   "landingZoneKickoffDelay":  "False",
                                   "opCodeEX":  "ID_DELAY",
                                   "time":  "0.03",
                                   "timeNGPM":  "0"
                               },
                      "type":  "DelayAssignment"
                  },
                  {
                      "guid":  "b6edb4c3-f809-4fcc-8ffe-121fa56e9526",
                      "data":  {
                                   "overrideFacingDirection":  "False",
                                   "direction":  "90",
                                   "distance":  "4",
                                   "facingDirectionOverride":  "0",
                                   "speed":  "100",
                                   "opCodeEX":  "ID_RECHANDOFF"
                               },
                      "type":  "ReceiveHandoffAssignment"
                  },
                  {
                      "guid":  "e0479afe-a656-4e1f-8211-89c59faed6e3",
                      "data":  {
                                   "flags":  "PassBlockFlags_None",
                                   "opCodeEX":  "ID_PASSBLOCK",
                                   "time":  "0"
                               },
                      "type":  "PassBlockAssignment"
                  },
                  {
                      "guid":  "0c44f6cc-17ad-45e0-977a-0f4babc6748e",
                      "data":  {
                                   "opCodeEX":  "ID_NONE"
                               },
                      "type":  "NoneAssignment"
                  }
              ]
}
