{
    "routeType":  "AssignRouteType_RB_Dive",
    "name":  "football/Playbooks/PlayLibrary/Assignments/Halfback/Wish_H3_HBIso",
    "steps":  [
                  {
                      "guid":  "134dd696-a8b0-41ed-9637-3cecf01fe9a4",
                      "data":  {
                                   "opCodeEX":  "ID_CANNEDHANDOFF",
                                   "handoffAnim":  "132",
                                   "playerNum":  "HandoffPlayerSlot_O1",
                                   "flippedHandoffAnim":  "133"
                               },
                      "type":  "CannedHandoffAssignment"
                  },
                  {
                      "guid":  "3a2a1d82-780b-4128-bb78-0fff5e26ab8c",
                      "data":  {
                                   "optionalInitalDirection":  "-1",
                                   "opCodeEX":  "ID_INITIALMOVE",
                                   "anim":  "MOVETYPE_HB_LATERAL_STEP",
                                   "direction":  "180"
                               },
                      "type":  "InitialAnimAssignment"
                  },
                  {
                      "guid":  "545d419d-2f1b-4a19-8a9e-127f7e33e5d4",
                      "data":  {
                                   "overrideFacingDirection":  "False",
                                   "direction":  "145",
                                   "distance":  "5",
                                   "facingDirectionOverride":  "0",
                                   "speed":  "68",
                                   "opCodeEX":  "ID_RECHANDOFF"
                               },
                      "type":  "ReceiveHandoffAssignment"
                  },
                  {
                      "guid":  "62c18f6f-db0d-4429-b5ca-e5d457c57bb7",
                      "data":  {
                                   "opCodeEX":  "ID_RUNEZ"
                               },
                      "type":  "RunEndZoneAssignment"
                  },
                  {
                      "guid":  "c3d3b351-6cf0-41ee-adb9-271a4c3d68d1",
                      "data":  {
                                   "opCodeEX":  "ID_NONE"
                               },
                      "type":  "NoneAssignment"
                  }
              ]
}
