{
    "routeType":  "AssignRouteType_RR_Corner_Deep",
    "name":  "football/Playbooks/PlayLibrary/Assignments/HotRoute/MUTSlotCorner_Right",
    "steps":  [
                  {
                      "guid":  "7f6cd652-e181-44e8-9f0b-eb52d8deb66a",
                      "data":  {
                                   "overrideFacingDirection":  "False",
                                   "direction":  "90",
                                   "distance":  "10",
                                   "facingDirectionOverride":  "0",
                                   "speed":  "100",
                                   "opCodeEX":  "ID_RUNROUTE"
                               },
                      "type":  "RunRouteAssignment"
                  },
                  {
                      "guid":  "e3a2fd34-d9b5-4e93-bc23-1205af5d0853",
                      "data":  {
                                   "cutType":  "RECEIVER_CUT_ANGLE_45",
                                   "opCodeEX":  "ID_RECCUT",
                                   "direction":  "RECEIVER_CUT_DIR_RIGHT"
                               },
                      "type":  "ReceiverCutAssignment"
                  },
                  {
                      "guid":  "1030dccc-48a6-4158-8614-ed87fc7ec6ce",
                      "data":  {
                                   "overrideFacingDirection":  "False",
                                   "direction":  "45",
                                   "distance":  "30",
                                   "facingDirectionOverride":  "0",
                                   "speed":  "100",
                                   "opCodeEX":  "ID_RUNROUTE"
                               },
                      "type":  "RunRouteAssignment"
                  },
                  {
                      "guid":  "9c27bb98-6250-4df9-9d6a-fbc12c8fc6cc",
                      "data":  {
                                   "opCodeEX":  "ID_RECGETOPEN"
                               },
                      "type":  "GetOpenAssignment"
                  },
                  {
                      "guid":  "732f361a-1814-4d8a-a3d4-cf3aa90d5336",
                      "data":  {
                                   "opCodeEX":  "ID_NONE"
                               },
                      "type":  "NoneAssignment"
                  }
              ]
}
