{
    "routeType":  "AssignRouteType_Block_Run",
    "name":  "football/Playbooks/PlayLibrary/Assignments/OverrideFormPos/BL_ALL_Wham90for0_TE_at_RtSlot_TightSlots_AutoMotion",
    "steps":  [
                  {
                      "guid":  "e7faee30-b962-4523-8d81-4153660c296c",
                      "data":  {
                                   "offsetY":  "-2.2",
                                   "opCodeEX":  "ID_OVERRIDEFORMPOS",
                                   "offsetX":  "5",
                                   "stance":  "TwoPoint"
                               },
                      "type":  "OverrideFormPosAssignment"
                  },
                  {
                      "guid":  "36a37ad5-4243-477e-bd17-b56233bdb7ed",
                      "data":  {
                                   "shouldStopAtTarget":  "False",
                                   "offsetX":  "4",
                                   "opCodeEX":  "ID_AUTOMOTION",
                                   "speed":  "35",
                                   "offsetY":  "2.5",
                                   "stanceAtTarget":  "StanceType_None"
                               },
                      "type":  "AutoMotionAssignment"
                  },
                  {
                      "guid":  "63bd0b95-92b6-40c7-9f42-4674fc7de4d3",
                      "data":  {
                                   "opCodeEX":  "ID_AUTOMOTIONSNAP"
                               },
                      "type":  "AutoMotionSnapAssignment"
                  },
                  {
                      "guid":  "9604f975-02ed-41e5-aa19-c467717ad0a4",
                      "data":  {
                                   "blockingGap":  "RUN_HOLE",
                                   "opCodeEX":  "ID_LEADBLOCK",
                                   "blockingTechnique":  "BLOCKINGTECHNIQUE_WHAM"
                               },
                      "type":  "LeadBlockAssignment"
                  },
                  {
                      "guid":  "85742552-1080-4d0c-b550-33f13e3508a1",
                      "data":  {
                                   "opCodeEX":  "ID_NONE"
                               },
                      "type":  "NoneAssignment"
                  }
              ]
}
