{
    "routeType":  "AssignRouteType_Block_Run",
    "name":  "football/Playbooks/PlayLibrary/Assignments/Blocking/Automotion_Lead140for03_WingFB_WeakI",
    "steps":  [
                  {
                      "guid":  "3199c171-9af7-4f9c-8ab2-d41791fbdb70",
                      "data":  {
                                   "shouldStopAtTarget":  "False",
                                   "offsetX":  "0",
                                   "opCodeEX":  "ID_AUTOMOTION",
                                   "speed":  "55",
                                   "offsetY":  "-3.35",
                                   "stanceAtTarget":  "StanceType_None"
                               },
                      "type":  "AutoMotionAssignment"
                  },
                  {
                      "guid":  "80716ec7-e4c8-432f-ab92-082c13217d48",
                      "data":  {
                                   "shouldStopAtTarget":  "False",
                                   "offsetX":  "-2",
                                   "opCodeEX":  "ID_AUTOMOTION",
                                   "speed":  "25",
                                   "offsetY":  "4",
                                   "stanceAtTarget":  "StanceType_None"
                               },
                      "type":  "AutoMotionAssignment"
                  },
                  {
                      "guid":  "bb69b7e3-ec63-4727-85aa-1a9f70d9931c",
                      "data":  {
                                   "opCodeEX":  "ID_AUTOMOTIONSNAP"
                               },
                      "type":  "AutoMotionSnapAssignment"
                  },
                  {
                      "guid":  "62cedb35-38fb-4111-a119-5fe258cd3c0b",
                      "data":  {
                                   "landingZoneKickoffDelay":  "False",
                                   "opCodeEX":  "ID_DELAY",
                                   "time":  "0.25",
                                   "timeNGPM":  "0"
                               },
                      "type":  "DelayAssignment"
                  },
                  {
                      "guid":  "65b9364b-7fa2-4b8b-9f2a-50ed1943bc8a",
                      "data":  {
                                   "blockingGap":  "RUN_HOLE",
                                   "opCodeEX":  "ID_LEADBLOCK",
                                   "blockingTechnique":  "BLOCKINGTECHNIQUE_COUNTER_KICKOUT"
                               },
                      "type":  "LeadBlockAssignment"
                  },
                  {
                      "guid":  "898c41ae-2e8c-47d7-9820-5184cb4b10e3",
                      "data":  {
                                   "opCodeEX":  "ID_NONE"
                               },
                      "type":  "NoneAssignment"
                  }
              ]
}
