{
    "routeType":  "AssignRouteType_RR_Slant_Hook",
    "name":  "football/Playbooks/PlayLibrary/Assignments/RunRoute/AutoMotion_WR_RighttoLeft_HookLt_(1)",
    "steps":  [
                  {
                      "guid":  "0d6c99d0-042f-42c6-b151-d61cdd8bfcaf",
                      "data":  {
                                   "waypoints":  "11-2.50550AUTOMOTIONLOCOSTYLE_NORMALTrue9.5-2.503290AUTOMOTIONLOCOSTYLE_STRAFEFalse",
                                   "shouldStopAtTarget":  "False",
                                   "automotionOrderPlayer":  "0",
                                   "automotionOrderTransitID":  "1",
                                   "endDelay":  "0",
                                   "useLegacyLocoPathing":  "False",
                                   "opCodeEX":  "ID_AUTOMOTION",
                                   "startDelay":  "0",
                                   "startEvent":  "AUTOMOTIONSTARTEVENT_SNAP",
                                   "stanceAtTarget":  "StanceType_None"
                               },
                      "type":  "AutoMotionAssignment"
                  },
                  {
                      "guid":  "7f34ea0c-8ebf-48eb-b4c3-5dd2ce859935",
                      "data":  {
                                   "landingZoneKickoffDelay":  "False",
                                   "opCodeEX":  "ID_DELAY",
                                   "time":  "0.27",
                                   "timeNGPM":  "0"
                               },
                      "type":  "DelayAssignment"
                  },
                  {
                      "guid":  "e36daf35-0187-4b95-b88a-a2978a2ded0b",
                      "data":  {
                                   "overrideFacingDirection":  "False",
                                   "direction":  "120",
                                   "distance":  "4.5",
                                   "facingDirectionOverride":  "0",
                                   "speed":  "100",
                                   "opCodeEX":  "ID_RUNROUTE"
                               },
                      "type":  "RunRouteAssignment"
                  },
                  {
                      "guid":  "07652c7a-3cdf-4d03-8b01-4a50af66cc9b",
                      "data":  {
                                   "cutType":  "RECEIVER_CUT_ANGLE_180_PARTIAL",
                                   "opCodeEX":  "ID_RECCUT",
                                   "direction":  "RECEIVER_CUT_DIR_LEFT"
                               },
                      "type":  "ReceiverCutAssignment"
                  },
                  {
                      "guid":  "a11278df-6813-42a7-ba4d-1ca411dfb68b",
                      "data":  {
                                   "landingZoneKickoffDelay":  "False",
                                   "opCodeEX":  "ID_DELAY",
                                   "time":  "1",
                                   "timeNGPM":  "0"
                               },
                      "type":  "DelayAssignment"
                  },
                  {
                      "guid":  "e0b31f41-1d97-4aad-bf27-40d692bc5941",
                      "data":  {
                                   "opCodeEX":  "ID_RECGETOPEN"
                               },
                      "type":  "GetOpenAssignment"
                  },
                  {
                      "guid":  "f151c3e7-e5fb-46f3-9d42-d3cc1b081dc8",
                      "data":  {
                                   "opCodeEX":  "ID_NONE"
                               },
                      "type":  "NoneAssignment"
                  }
              ]
}
