{
    "routeType":  "AssignRouteType_RR_Flat_Lt",
    "name":  "football/Playbooks/PlayLibrary/Assignments/RunRoute/TE_FlatsLt_Slide",
    "steps":  [
                  {
                      "guid":  "423b767f-8506-4b71-882a-a0f6ceb9b812",
                      "data":  {
                                   "overrideFacingDirection":  "False",
                                   "direction":  "180",
                                   "distance":  "7",
                                   "facingDirectionOverride":  "0",
                                   "speed":  "100",
                                   "opCodeEX":  "ID_RUNROUTE"
                               },
                      "type":  "RunRouteAssignment"
                  },
                  {
                      "guid":  "79d84271-a286-4ffb-9ae5-0585e0af12fa",
                      "data":  {
                                   "overrideFacingDirection":  "False",
                                   "direction":  "164",
                                   "distance":  "20",
                                   "facingDirectionOverride":  "0",
                                   "speed":  "100",
                                   "opCodeEX":  "ID_RUNROUTE"
                               },
                      "type":  "RunRouteAssignment"
                  },
                  {
                      "guid":  "d46032f7-2feb-4305-9be9-4e9f4bb87bfc",
                      "data":  {
                                   "landingZoneKickoffDelay":  "False",
                                   "opCodeEX":  "ID_DELAY",
                                   "time":  "2",
                                   "timeNGPM":  "0"
                               },
                      "type":  "DelayAssignment"
                  },
                  {
                      "guid":  "eaf0483b-51cc-4823-87e5-9005446bc9c1",
                      "data":  {
                                   "opCodeEX":  "ID_RECGETOPEN"
                               },
                      "type":  "GetOpenAssignment"
                  },
                  {
                      "guid":  "27a58f98-333d-40eb-8244-24ea991d9b9f",
                      "data":  {
                                   "opCodeEX":  "ID_NONE"
                               },
                      "type":  "NoneAssignment"
                  }
              ]
}
