{
    "routeType":  "AssignRouteType_RR_Wheel_Lt",
    "name":  "football/Playbooks/PlayLibrary/Assignments/RunRoute/WR_Run150for06_Run90for25_5WRBunch_Slot_Wheel",
    "steps":  [
                  {
                      "guid":  "81b9f9fa-5966-447e-b7cf-a8b909e927f8",
                      "data":  {
                                   "overrideFacingDirection":  "False",
                                   "direction":  "90",
                                   "distance":  "0.25",
                                   "facingDirectionOverride":  "0",
                                   "speed":  "100",
                                   "opCodeEX":  "ID_RUNROUTE"
                               },
                      "type":  "RunRouteAssignment"
                  },
                  {
                      "guid":  "780966ea-eece-49c3-835a-9ddc8585da3b",
                      "data":  {
                                   "overrideFacingDirection":  "False",
                                   "direction":  "135",
                                   "distance":  "6.25",
                                   "facingDirectionOverride":  "0",
                                   "speed":  "100",
                                   "opCodeEX":  "ID_RUNROUTE"
                               },
                      "type":  "RunRouteAssignment"
                  },
                  {
                      "guid":  "c8989705-f7cb-4cce-ae84-872e7126c9b6",
                      "data":  {
                                   "cutType":  "RECEIVER_CUT_ANGLE_45",
                                   "opCodeEX":  "ID_RECCUT",
                                   "direction":  "RECEIVER_CUT_DIR_RIGHT"
                               },
                      "type":  "ReceiverCutAssignment"
                  },
                  {
                      "guid":  "afe87639-68e2-4eab-b30c-a932056c0dcd",
                      "data":  {
                                   "overrideFacingDirection":  "False",
                                   "direction":  "93",
                                   "distance":  "25",
                                   "facingDirectionOverride":  "0",
                                   "speed":  "100",
                                   "opCodeEX":  "ID_RUNROUTE"
                               },
                      "type":  "RunRouteAssignment"
                  },
                  {
                      "guid":  "fc04f6f3-15e2-4daf-ba3d-00e02b79686b",
                      "data":  {
                                   "opCodeEX":  "ID_RECGETOPEN"
                               },
                      "type":  "GetOpenAssignment"
                  },
                  {
                      "guid":  "68fa51b3-8ac1-45f3-af3d-0280f68c5562",
                      "data":  {
                                   "opCodeEX":  "ID_NONE"
                               },
                      "type":  "NoneAssignment"
                  }
              ]
}
