{
    "firstPreSnapMovementPositions":  [
                                          {
                                              "motionShuffleBetweenTackles":  false,
                                              "YPos":  -1.4,
                                              "XPos":  0,
                                              "anim":  "StanceType_QB_Before_Play",
                                              "flippedYPos":  -1.4,
                                              "facing":  90,
                                              "posOrder":  0,
                                              "guid":  "1f3b9dcc-6a82-4cd8-9d2c-a79d0a00582f",
                                              "depthPosition":  "POSITION_QB",
                                              "depth":  1,
                                              "groupType":  "Set_Group_Type_Quarterback",
                                              "cpuKickBlocker":  false,
                                              "flippedXPos":  0,
                                              "flippedAnim":  "StanceType_QB_Before_Play",
                                              "userKickBlocker":  false,
                                              "flippedFacing":  90,
                                              "primaryMotionMan":  false,
                                              "flipAssign":  0
                                          },
                                          {
                                              "motionShuffleBetweenTackles":  false,
                                              "YPos":  -7.375,
                                              "XPos":  0,
                                              "anim":  "StanceType_2pt",
                                              "flippedYPos":  -7.375,
                                              "facing":  90,
                                              "posOrder":  1,
                                              "guid":  "a9ab68be-09d5-42e0-a4b8-e4ede6945f43",
                                              "depthPosition":  "POSITION_HB",
                                              "depth":  1,
                                              "groupType":  "Set_Group_Type_MotionMan3",
                                              "cpuKickBlocker":  false,
                                              "flippedXPos":  0,
                                              "flippedAnim":  "StanceType_2pt",
                                              "userKickBlocker":  false,
                                              "flippedFacing":  90,
                                              "primaryMotionMan":  true,
                                              "flipAssign":  1
                                          },
                                          {
                                              "motionShuffleBetweenTackles":  false,
                                              "YPos":  -2.2,
                                              "XPos":  -5,
                                              "anim":  "StanceType_3pt",
                                              "flippedYPos":  -2.2,
                                              "facing":  90,
                                              "posOrder":  2,
                                              "guid":  "f7f767b5-feb7-4d25-8da5-8c7e703cca83",
                                              "depthPosition":  "POSITION_LASTKEYOFFENSE",
                                              "depth":  2,
                                              "groupType":  "Set_Group_Type_MotionMan2",
                                              "cpuKickBlocker":  false,
                                              "flippedXPos":  -5,
                                              "flippedAnim":  "StanceType_3pt",
                                              "userKickBlocker":  false,
                                              "flippedFacing":  90,
                                              "primaryMotionMan":  false,
                                              "flipAssign":  5
                                          },
                                          {
                                              "motionShuffleBetweenTackles":  false,
                                              "YPos":  -0.8,
                                              "XPos":  -15,
                                              "anim":  "StanceType_2pt",
                                              "flippedYPos":  -0.8,
                                              "facing":  90,
                                              "posOrder":  3,
                                              "guid":  "77b521a3-b78c-49aa-a66c-3673e6b56990",
                                              "depthPosition":  "POSITION_WR",
                                              "depth":  1,
                                              "groupType":  "Set_Group_Type_MotionMan1",
                                              "cpuKickBlocker":  false,
                                              "flippedXPos":  -15,
                                              "flippedAnim":  "StanceType_2pt",
                                              "userKickBlocker":  false,
                                              "flippedFacing":  90,
                                              "primaryMotionMan":  false,
                                              "flipAssign":  4
                                          },
                                          {
                                              "motionShuffleBetweenTackles":  false,
                                              "YPos":  -0.8,
                                              "XPos":  15,
                                              "anim":  "StanceType_2pt",
                                              "flippedYPos":  -0.8,
                                              "facing":  90,
                                              "posOrder":  4,
                                              "guid":  "4f3c2d65-2001-4000-8371-31d2ecc5de7d",
                                              "depthPosition":  "POSITION_WR",
                                              "depth":  2,
                                              "groupType":  "Set_Group_Type_MotionMan5",
                                              "cpuKickBlocker":  false,
                                              "flippedXPos":  15,
                                              "flippedAnim":  "StanceType_2pt",
                                              "userKickBlocker":  false,
                                              "flippedFacing":  90,
                                              "primaryMotionMan":  false,
                                              "flipAssign":  3
                                          },
                                          {
                                              "motionShuffleBetweenTackles":  false,
                                              "YPos":  -2.2,
                                              "XPos":  5,
                                              "anim":  "StanceType_3pt",
                                              "flippedYPos":  -2.2,
                                              "facing":  90,
                                              "posOrder":  5,
                                              "guid":  "bb3a38eb-a1ff-4d22-81ec-074a7d34422d",
                                              "depthPosition":  "POSITION_LASTKEYOFFENSE",
                                              "depth":  1,
                                              "groupType":  "Set_Group_Type_MotionMan4",
                                              "cpuKickBlocker":  false,
                                              "flippedXPos":  5,
                                              "flippedAnim":  "StanceType_3pt",
                                              "userKickBlocker":  false,
                                              "flippedFacing":  90,
                                              "primaryMotionMan":  true,
                                              "flipAssign":  2
                                          },
                                          {
                                              "motionShuffleBetweenTackles":  false,
                                              "YPos":  -1,
                                              "XPos":  -3.333,
                                              "anim":  "StanceType_3pt",
                                              "flippedYPos":  -1,
                                              "facing":  90,
                                              "posOrder":  6,
                                              "guid":  "221d2a0d-4d6d-442b-936f-d5f9a8a3f073",
                                              "depthPosition":  "POSITION_FIRSTOFFENSELINE",
                                              "depth":  1,
                                              "groupType":  "Set_Group_Type_Linemen",
                                              "cpuKickBlocker":  false,
                                              "flippedXPos":  -3.333,
                                              "flippedAnim":  "StanceType_3pt",
                                              "userKickBlocker":  false,
                                              "flippedFacing":  90,
                                              "primaryMotionMan":  false,
                                              "flipAssign":  10
                                          },
                                          {
                                              "motionShuffleBetweenTackles":  false,
                                              "YPos":  -0.9,
                                              "XPos":  -1.666,
                                              "anim":  "StanceType_3pt",
                                              "flippedYPos":  -0.9,
                                              "facing":  90,
                                              "posOrder":  7,
                                              "guid":  "7f7fe7a0-daaa-4242-90c2-e90f0dfe19db",
                                              "depthPosition":  "POSITION_LG",
                                              "depth":  1,
                                              "groupType":  "Set_Group_Type_Linemen",
                                              "cpuKickBlocker":  false,
                                              "flippedXPos":  -1.666,
                                              "flippedAnim":  "StanceType_3pt",
                                              "userKickBlocker":  false,
                                              "flippedFacing":  90,
                                              "primaryMotionMan":  false,
                                              "flipAssign":  9
                                          },
                                          {
                                              "motionShuffleBetweenTackles":  false,
                                              "YPos":  -0.6,
                                              "XPos":  0,
                                              "anim":  "StanceType_3pt",
                                              "flippedYPos":  -0.6,
                                              "facing":  90,
                                              "posOrder":  8,
                                              "guid":  "fc9103a7-2a4f-415a-ba9a-a3086d5e62e2",
                                              "depthPosition":  "POSITION_C",
                                              "depth":  1,
                                              "groupType":  "Set_Group_Type_Linemen",
                                              "cpuKickBlocker":  false,
                                              "flippedXPos":  0,
                                              "flippedAnim":  "StanceType_3pt",
                                              "userKickBlocker":  false,
                                              "flippedFacing":  90,
                                              "primaryMotionMan":  false,
                                              "flipAssign":  8
                                          },
                                          {
                                              "motionShuffleBetweenTackles":  false,
                                              "YPos":  -0.9,
                                              "XPos":  1.666,
                                              "anim":  "StanceType_3pt",
                                              "flippedYPos":  -0.9,
                                              "facing":  90,
                                              "posOrder":  9,
                                              "guid":  "ddece9c6-6892-41b4-9f0f-eb2cca78af5a",
                                              "depthPosition":  "POSITION_RG",
                                              "depth":  1,
                                              "groupType":  "Set_Group_Type_Linemen",
                                              "cpuKickBlocker":  false,
                                              "flippedXPos":  1.666,
                                              "flippedAnim":  "StanceType_3pt",
                                              "userKickBlocker":  false,
                                              "flippedFacing":  90,
                                              "primaryMotionMan":  false,
                                              "flipAssign":  7
                                          },
                                          {
                                              "motionShuffleBetweenTackles":  false,
                                              "YPos":  -1,
                                              "XPos":  3.333,
                                              "anim":  "StanceType_3pt",
                                              "flippedYPos":  -1,
                                              "facing":  90,
                                              "posOrder":  10,
                                              "guid":  "dc94f001-d751-43a4-b1db-39258869ddea",
                                              "depthPosition":  "POSITION_LASTOFFENSELINE",
                                              "depth":  1,
                                              "groupType":  "Set_Group_Type_Linemen",
                                              "cpuKickBlocker":  false,
                                              "flippedXPos":  3.333,
                                              "flippedAnim":  "StanceType_3pt",
                                              "userKickBlocker":  false,
                                              "flippedFacing":  90,
                                              "primaryMotionMan":  false,
                                              "flipAssign":  6
                                          }
                                      ],
    "formationInfo":  {
                          "namePath":  "football/Playbooks/PlayLibrary/Formations/Offense/Singleback/Deuce/Deuce",
                          "guid":  "d73bd77e-7237-4d47-a93f-b66bd9b58ada",
                          "setName":  "Deuce"
                      },
    "firstPreSnapMovementDetails":  {
                                        "type":  "PreSnapMovementType_Normal",
                                        "isDefault":  true,
                                        "guid":  "f0017353-a491-48e9-9511-1fc898c1c72d",
                                        "name":  "Normal"
                                    }
}
